src/__init__.py
src/main.py
src/model/__init__.py
src/model/model.py
src/model/system_prompt.txt
src/model/tools.py
src/shell/__init__.py
src/shell/alias.py
src/shell/completions.py
src/shell/history.py
src/shell/input.py
src/shell/shell.py
src/utils/__init__.py
src/utils/config.py
src/utils/debug.py
src/utils/dictation.py
src/utils/message_cache.py
src/utils/permissions.py
src/utils/rules.py
src/utils/token_counter.py
termagent-0.1.0.dist-info/METADATA
termagent-0.1.0.dist-info/WHEEL
termagent-0.1.0.dist-info/entry_points.txt
termagent-0.1.0.dist-info/licenses/LICENSE
termagent-0.1.0.dist-info/RECORD
