Metadata-Version: 2.4
Name: termagent
Version: 0.1.0
Summary: A Python package for terminal agent functionality
License: MIT
License-File: LICENSE
Requires-Python: >=3.11
Requires-Dist: anthropic>=0.40.0
Requires-Dist: bumpver>=2025.1131
Requires-Dist: pydantic>=2.0.0
Requires-Dist: rich>=13.0.0
Requires-Dist: tiktoken>=0.5.0
